bstephe9_example_project/__init__.py
bstephe9_example_project/foo.py
bstephe9_example_project-1.0.1.dist-info/METADATA
bstephe9_example_project-1.0.1.dist-info/WHEEL
bstephe9_example_project-1.0.1.dist-info/licenses/LICENSE
bstephe9_example_project-1.0.1.dist-info/RECORD
