Metadata-Version: 2.4
Name: bstephe9-example-project
Version: 1.0.1
Summary: This is a template repository for Python projects that use uv for their dependency management.
Project-URL: Homepage, https://bstephe9.github.io/bstephe9-example-project/
Project-URL: Repository, https://github.com/bstephe9/bstephe9-example-project
Project-URL: Documentation, https://bstephe9.github.io/bstephe9-example-project/
Author-email: Ben Stephenson <bstephenson9807@gmail.com>
License-File: LICENSE
Keywords: python
Classifier: Intended Audience :: Developers
Classifier: Programming Language :: Python
Classifier: Programming Language :: Python :: 3
Classifier: Programming Language :: Python :: 3.9
Classifier: Programming Language :: Python :: 3.10
Classifier: Programming Language :: Python :: 3.11
Classifier: Programming Language :: Python :: 3.12
Classifier: Programming Language :: Python :: 3.13
Classifier: Topic :: Software Development :: Libraries :: Python Modules
Requires-Python: <4.0,>=3.9
